README.txt
setup.py
collective/__init__.py
collective.jqueryui.autocomplete.egg-info/PKG-INFO
collective.jqueryui.autocomplete.egg-info/SOURCES.txt
collective.jqueryui.autocomplete.egg-info/dependency_links.txt
collective.jqueryui.autocomplete.egg-info/entry_points.txt
collective.jqueryui.autocomplete.egg-info/namespace_packages.txt
collective.jqueryui.autocomplete.egg-info/not-zip-safe
collective.jqueryui.autocomplete.egg-info/requires.txt
collective.jqueryui.autocomplete.egg-info/top_level.txt
collective/jqueryui/__init__.py
collective/jqueryui/autocomplete/__init__.py
collective/jqueryui/autocomplete/configure.zcml
collective/jqueryui/autocomplete/tests.py
collective/jqueryui/autocomplete/Extensions/install.py
collective/jqueryui/autocomplete/browser/__init__.py
collective/jqueryui/autocomplete/browser/configure.zcml
collective/jqueryui/autocomplete/browser/jquery-ui-1.8.16.custom.min.js
collective/jqueryui/autocomplete/browser/base/jquery.ui.all.css
collective/jqueryui/autocomplete/browser/base/jquery.ui.autocomplete.css
collective/jqueryui/autocomplete/browser/base/jquery.ui.base.css
collective/jqueryui/autocomplete/browser/base/jquery.ui.core.css
collective/jqueryui/autocomplete/browser/base/jquery.ui.theme.css
collective/jqueryui/autocomplete/browser/base/images/ui-bg_flat_0_aaaaaa_40x100.png
collective/jqueryui/autocomplete/browser/base/images/ui-bg_flat_75_ffffff_40x100.png
collective/jqueryui/autocomplete/browser/base/images/ui-bg_glass_55_fbf9ee_1x400.png
collective/jqueryui/autocomplete/browser/base/images/ui-bg_glass_65_ffffff_1x400.png
collective/jqueryui/autocomplete/browser/base/images/ui-bg_glass_75_dadada_1x400.png
collective/jqueryui/autocomplete/browser/base/images/ui-bg_glass_75_e6e6e6_1x400.png
collective/jqueryui/autocomplete/browser/base/images/ui-bg_glass_95_fef1ec_1x400.png
collective/jqueryui/autocomplete/browser/base/images/ui-bg_highlight-soft_75_cccccc_1x100.png
collective/jqueryui/autocomplete/browser/base/images/ui-icons_222222_256x240.png
collective/jqueryui/autocomplete/browser/base/images/ui-icons_2e83ff_256x240.png
collective/jqueryui/autocomplete/browser/base/images/ui-icons_454545_256x240.png
collective/jqueryui/autocomplete/browser/base/images/ui-icons_888888_256x240.png
collective/jqueryui/autocomplete/browser/base/images/ui-icons_cd0a0a_256x240.png
collective/jqueryui/autocomplete/profiles/default/cssregistry.xml
