Metadata-Version: 1.0
Name: collective.jqueryui.autocomplete
Version: 0.1.0
Summary: jQueryUI for Plone, limited at minimal to provide only autocomplete feature
Home-page: http://plone.org/products/collective.jqueryui.autocomplete
Author: RedTurtle Technology
Author-email: sviluppoplone@redturtle.it
License: GPL
Keywords: plone jquery jqueryui plonegov
Platform: UNKNOWN
Classifier: Framework :: Plone
Classifier: Framework :: Plone :: 3.3
Classifier: Programming Language :: Python
Classifier: Programming Language :: JavaScript
